rotatescreen/__init__.py
rotatescreen/display.py
rotatescreen/display_linux.py
rotate_screen-0.1.5.dist-info/LICENSE
rotate_screen-0.1.5.dist-info/METADATA
rotate_screen-0.1.5.dist-info/WHEEL
rotate_screen-0.1.5.dist-info/top_level.txt
rotate_screen-0.1.5.dist-info/RECORD
