Metadata-Version: 2.1
Name: rotate-screen
Version: 0.1.5
Summary: A small Python package for rotating the screen.
Home-page: https://github.com/danny-burrows/rotate-screen
Author: Danny Burrows
Author-email: dannyburrows@protonmail.com
License: MIT
Classifier: License :: OSI Approved :: MIT License
Classifier: Operating System :: Microsoft :: Windows
Classifier: Topic :: Desktop Environment
Classifier: Programming Language :: Python
Classifier: Programming Language :: Python :: 3
Classifier: Programming Language :: Python :: 3 :: Only
Classifier: Programming Language :: Python :: 3.7
Classifier: Programming Language :: Python :: 3.8
Classifier: Programming Language :: Python :: 3.9
Classifier: Programming Language :: Python :: 3.10
Classifier: Programming Language :: Python :: 3.11
Classifier: Programming Language :: Python :: 3.12
Requires-Python: >=3.7.0
License-File: LICENSE
Requires-Dist: pywin32 ; platform_system == "Windows"
Provides-Extra: shortcuts_example
Requires-Dist: keyboard ; extra == 'shortcuts_example'
